afwfcfg/__init__.py
afwfcfg/afwf_config.py
afwfcfg/afwf_evilTypeAction_config.py
afwfcfg/afwf_get_update_count.py
afwfcfg/afwf_log.py
afwfcfg/black_white_list.py
afwfcfg/devbind.py
afwfcfg/version_config.py
afwfcfg-2.0.1.dist-info/METADATA
afwfcfg-2.0.1.dist-info/WHEEL
afwfcfg-2.0.1.dist-info/entry_points.txt
afwfcfg-2.0.1.dist-info/top_level.txt
afwfcfg-2.0.1.dist-info/RECORD
