Metadata-Version: 2.1
Name: afwfcfg
Version: 2.0.1
Summary: afwf config module
Home-page: UNKNOWN
Author: UNKNOWN
Author-email: UNKNOWN
License: UNKNOWN
Platform: UNKNOWN
